ews_folder_cleaner/__init__.py
ews_folder_cleaner/exchange_cleaner_linux_fixed.py
ews_folder_cleaner-1.0.1.dist-info/METADATA
ews_folder_cleaner-1.0.1.dist-info/WHEEL
ews_folder_cleaner-1.0.1.dist-info/entry_points.txt
ews_folder_cleaner-1.0.1.dist-info/top_level.txt
ews_folder_cleaner-1.0.1.dist-info/RECORD
