Metadata-Version: 2.4
Name: ews-folder-cleaner
Version: 1.0.1
Summary: A powerful utility for cleaning and managing Exchange mailbox folders via EWS
Home-page: https://github.com/dobeyman/ews_folder_cleaner
Author: Jenre
Author-email: je@n-remy.ovh
Classifier: Programming Language :: Python :: 3
Classifier: License :: OSI Approved :: MIT License
Classifier: Operating System :: OS Independent
Requires-Python: >=3.6
Requires-Dist: exchangelib
Requires-Dist: colorama
Requires-Dist: rich
Dynamic: author
Dynamic: author-email
Dynamic: classifier
Dynamic: description
Dynamic: description-content-type
Dynamic: home-page
Dynamic: requires-dist
Dynamic: requires-python
Dynamic: summary
